{
  "model": {
    "name": "star",
    "norm": "pn",
    "dense": "star",
    "auxiliary_net": false,
    "user_dim": 128,
    "item_dim": 128,
    "domain_dim": 128,
    "auxiliary_dim": 64,
    "hidden_dim": [
      256,
      128,
      64
    ]
  },
  "train": {
    "load_pretrain_emb": true,
    "emb_trainable": false,
    "epoch": 99999,
    "learning_rate": 0.001,
    "result_save_path": "result",
    "checkpoint_path": "checkpoint",
    "loss": "binary_crossentropy",
    "optimizer": "adam",
    "patience": 3,
    "histogram_freq": 0,
    "shuffle_buff_size": 10000
  },
  "dataset": {
    "name": "Taobao",
    "dataset_path": "dataset/Taobao",
    "domain_split_path": "split_by_theme_30",
    "batch_size": 1024,
    "shuffle_buffer_size": 10000,
    "num_parallel_reads": 8,
    "seed": 123
  }
}